<item sdImg="http://viper.demandvideo.com/media/83ea3c72-0eb2-408c-8c91-cb0453e26a05/jpeg/1e78f742-cda0-4f1f-a906-f592a011af2e_0.jpg" hdImg="http://viper.demandvideo.com/media/83ea3c72-0eb2-408c-8c91-cb0453e26a05/jpeg/1e78f742-cda0-4f1f-a906-f592a011af2e_0.jpg">
	<title>How to Determine if Given Coordinates Are Quadrilateral : Math Variables &amp; More</title>
	<contentId>1e78f742-cda0-4f1f-a906-f592a011af2e</contentId>
	<contentType>howto</contentType>
	<contentQuality>Jimmy Chang</contentQuality>
	<streamFormat>mov</streamFormat>
	<media>
		<streamQuality>SD</streamQuality>
		<streamBitrate>1500</streamBitrate>
		<streamUrl>http://viper.demandvideo.com/media/83ea3c72-0eb2-408c-8c91-cb0453e26a05/master/1e78f742-cda0-4f1f-a906-f592a011af2e.mov</streamUrl>
	</media>
	<synopsis>If given coordinates are quadrilaterals, you can prove this by looking at a few key things. Determine if given coordinates are quadrilateral with help from a longtime mathematics educator in this free video clip.</synopsis>
	<genres>Education</genres>
	<runtime>112</runtime>
</item>
